{"running": null, "toRun": {}, "order": [], "completed": {"anotherOneBitesTheBatchQueen": {"path": "/home/pietrotrope/Desktop/Github/dashboard", "dataset": "m10", "model": {"name": "LDA", "parameters": {"eta": 0.1, "iterations": 50, "num_topics": 10, "passes": 1}}, "optimization": {"iterations": 5, "model_runs": 3, "surrogate_model": "RF", "n_random_starts": 3, "acquisition_function": "LCB", "search_spaces": {"alpha": {"low": 0.3, "high": 5}}}, "optimize_metrics": [{"name": "Topic_diversity", "parameters": {"topk": 10}}], "track_metrics": [], "batchId": "anotherOneBitesTheBatch", "experimentId": "Queen"}, "coherenceWithStrangerThingsKing": {"path": "/home/pietrotrope/Desktop/Github/dashboard", "dataset": "m10", "model": {"name": "LDA", "parameters": {"iterations": 50, "num_topics": 10, "passes": 1}}, "optimization": {"iterations": 5, "model_runs": 3, "surrogate_model": "RF", "n_random_starts": 3, "acquisition_function": "LCB", "search_spaces": {"alpha": {"low": 2, "high": 6}, "eta": {"low": 0.1, "high": 6}}}, "optimize_metrics": [{"name": "Topic_diversity", "parameters": {"topk": 10}}], "track_metrics": [], "batchId": "coherenceWithStrangerThings", "experimentId": "King"}}}